_pypolychord.so
pypolychord_nompi-1.15.1.dist-info/WHEEL
pypolychord_nompi-1.15.1.dist-info/top_level.txt
pypolychord_nompi-1.15.1.dist-info/METADATA
pypolychord_nompi-1.15.1.dist-info/RECORD
pypolychord/priors.py
pypolychord/output.py
pypolychord/settings.py
pypolychord/__init__.py
pypolychord/libs_pypolychord/libchord-5b9c4da5.so
pypolychord/libs_pypolychord/libgfortran-ed201abd.so.3.0.0
